cvmmlst/__init__.py
cvmmlst/cvmmlst.py
cvmmlst/mlst.py
cvmmlst/mlstdb_setup.sh
cvmmlst/db/.DS_Store
cvmmlst/db/blast/mlst.fa
cvmmlst/db/blast/mlst.fa.ndb
cvmmlst/db/blast/mlst.fa.nhd
cvmmlst/db/blast/mlst.fa.nhi
cvmmlst/db/blast/mlst.fa.nhr
cvmmlst/db/blast/mlst.fa.nin
cvmmlst/db/blast/mlst.fa.njs
cvmmlst/db/blast/mlst.fa.nog
cvmmlst/db/blast/mlst.fa.nos
cvmmlst/db/blast/mlst.fa.not
cvmmlst/db/blast/mlst.fa.nsq
cvmmlst/db/blast/mlst.fa.ntf
cvmmlst/db/blast/mlst.fa.nto
cvmmlst/db/pubmlst/.DS_Store
cvmmlst/db/pubmlst/dbases.sh
cvmmlst/db/pubmlst/aactinomycetemcomitans/aactinomycetemcomitans.txt
cvmmlst/db/pubmlst/aactinomycetemcomitans/adk.tfa
cvmmlst/db/pubmlst/aactinomycetemcomitans/atpG.tfa
cvmmlst/db/pubmlst/aactinomycetemcomitans/frdB.tfa
cvmmlst/db/pubmlst/aactinomycetemcomitans/mdh.tfa
cvmmlst/db/pubmlst/aactinomycetemcomitans/pgi.tfa
cvmmlst/db/pubmlst/aactinomycetemcomitans/recA.tfa
cvmmlst/db/pubmlst/aactinomycetemcomitans/zwf.tfa
cvmmlst/db/pubmlst/abaumannii/Oxf_cpn60.tfa
cvmmlst/db/pubmlst/abaumannii/Oxf_gdhB.tfa
cvmmlst/db/pubmlst/abaumannii/Oxf_gltA.tfa
cvmmlst/db/pubmlst/abaumannii/Oxf_gpi.tfa
cvmmlst/db/pubmlst/abaumannii/Oxf_gyrB.tfa
cvmmlst/db/pubmlst/abaumannii/Oxf_recA.tfa
cvmmlst/db/pubmlst/abaumannii/Oxf_rpoD.tfa
cvmmlst/db/pubmlst/abaumannii/abaumannii.txt
cvmmlst/db/pubmlst/abaumannii_2/Pas_cpn60.tfa
cvmmlst/db/pubmlst/abaumannii_2/Pas_fusA.tfa
cvmmlst/db/pubmlst/abaumannii_2/Pas_gltA.tfa
cvmmlst/db/pubmlst/abaumannii_2/Pas_pyrG.tfa
cvmmlst/db/pubmlst/abaumannii_2/Pas_recA.tfa
cvmmlst/db/pubmlst/abaumannii_2/Pas_rplB.tfa
cvmmlst/db/pubmlst/abaumannii_2/Pas_rpoB.tfa
cvmmlst/db/pubmlst/abaumannii_2/abaumannii_2.txt
cvmmlst/db/pubmlst/achromobacter/achromobacter.txt
cvmmlst/db/pubmlst/achromobacter/eno.tfa
cvmmlst/db/pubmlst/achromobacter/gltB.tfa
cvmmlst/db/pubmlst/achromobacter/lepA.tfa
cvmmlst/db/pubmlst/achromobacter/nrdA.tfa
cvmmlst/db/pubmlst/achromobacter/nuoL.tfa
cvmmlst/db/pubmlst/achromobacter/nusA.tfa
cvmmlst-0.3.8.dist-info/METADATA
cvmmlst-0.3.8.dist-info/WHEEL
cvmmlst-0.3.8.dist-info/entry_points.txt
cvmmlst-0.3.8.dist-info/top_level.txt
cvmmlst-0.3.8.dist-info/RECORD
