Metadata-Version: 2.1
Name: cvmmlst
Version: 0.3.8
Summary: python mlst analysis tool
Home-page: https://github.com/hbucqp/cvmmlst
Author: Qingpo Cui
Author-email: cqp@cau.edu.cn
License: MIT Licence
Keywords: wgs,pubmlst,mlst
Platform: any
Classifier: Development Status :: 3 - Alpha
Classifier: Intended Audience :: Developers
Classifier: Topic :: Software Development :: Build Tools
Classifier: License :: OSI Approved :: MIT License
Classifier: Programming Language :: Python :: 3
Classifier: Programming Language :: Python :: 3.7
Classifier: Programming Language :: Python :: 3.8
Classifier: Programming Language :: Python :: 3.9
Requires-Dist: Bio
Requires-Dist: pandas
Requires-Dist: numpy
Requires-Dist: setuptools
Requires-Dist: cvmcore (>=0.2.0)
Requires-Dist: dask
Requires-Dist: tabulate
